{
    "timestamp": "2024-01-24T09:55:38Z",
    "previous_timestamp": "2024-01-24T09:50:38Z",
    "next_timestamp": "2024-01-24T10:00:39Z",
    "data": {
        "id": "27719644acb13e72e59e2541fa2cedc6",
        "sport_key": "basketball_nba",
        "sport_title": "NBA",
        "commence_time": "2024-01-25T00:40:00Z",
        "home_team": "Miami Heat",
        "away_team": "Memphis Grizzlies",
        "bookmakers": [
            {
                "key": "draftkings",
                "title": "DraftKings",
                "last_update": "2024-01-24T09:55:29Z",
                "markets": [
                    {
                        "key": "player_assists",
                        "last_update": "2024-01-24T09:54:52Z",
                        "outcomes": [
                            {
                                "name": "Over",
                                "description": "Bam Adebayo",
                                "price": 1.83,
                                "point": 4.5
                            },
                            {
                                "name": "Under",
                                "description": "Bam Adebayo",
                                "price": 1.91,
                                "point": 4.5
                            },
                            {
                                "name": "Over",
                                "description": "Jaren Jackson Jr.",
                                "price": 1.71,
                                "point": 2.5
                            },
                            {
                                "name": "Under",
                                "description": "Jaren Jackson Jr.",
                                "price": 2.1,
                                "point": 2.5
                            },
                            {
                                "name": "Over",
                                "description": "Luke Kennard",
                                "price": 1.91,
                                "point": 4.5
                            },
                            {
                                "name": "Under",
                                "description": "Luke Kennard",
                                "price": 1.83,
                                "point": 4.5
                            },
                            {
                                "name": "Over",
                                "description": "Tyler Herro",
                                "price": 1.95,
                                "point": 3.5
                            },
                            {
                                "name": "Under",
                                "description": "Tyler Herro",
                                "price": 1.8,
                                "point": 3.5
                            },
                            {
                                "name": "Over",
                                "description": "Vince Williams Jr.",
                                "price": 1.62,
                                "point": 3.5
                            },
                            {
                                "name": "Under",
                                "description": "Vince Williams Jr.",
                                "price": 2.24,
                                "point": 3.5
                            },
                            {
                                "name": "Over",
                                "description": "Xavier Tillman",
                                "price": 2.35,
                                "point": 3.5
                            },
                            {
                                "name": "Under",
                                "description": "Xavier Tillman",
                                "price": 1.57,
                                "point": 3.5
                            }
                        ]
                    },
                    {
                        "key": "player_points",
                        "last_update": "2024-01-24T09:54:52Z",
                        "outcomes": [
                            {
                                "name": "Over",
                                "description": "Bam Adebayo",
                                "price": 1.8,
                                "point": 20.5
                            },
                            {
                                "name": "Under",
                                "description": "Bam Adebayo",
                                "price": 1.95,
                                "point": 20.5
                            },
                            {
                                "name": "Over",
                                "description": "Jaren Jackson Jr.",
                                "price": 1.8,
                                "point": 25.5
                            },
                            {
                                "name": "Under",
                                "description": "Jaren Jackson Jr.",
                                "price": 1.95,
                                "point": 25.5
                            },
                            {
                                "name": "Over",
                                "description": "Luke Kennard",
                                "price": 1.91,
                                "point": 15.5
                            },
                            {
                                "name": "Under",
                                "description": "Luke Kennard",
                                "price": 1.83,
                                "point": 15.5
                            },
                            {
                                "name": "Over",
                                "description": "Tyler Herro",
                                "price": 1.71,
                                "point": 20.5
                            },
                            {
                                "name": "Under",
                                "description": "Tyler Herro",
                                "price": 2.1,
                                "point": 20.5
                            },
                            {
                                "name": "Over",
                                "description": "Vince Williams Jr.",
                                "price": 1.87,
                                "point": 12.5
                            },
                            {
                                "name": "Under",
                                "description": "Vince Williams Jr.",
                                "price": 1.87,
                                "point": 12.5
                            },
                            {
                                "name": "Over",
                                "description": "Xavier Tillman",
                                "price": 1.87,
                                "point": 10.5
                            },
                            {
                                "name": "Under",
                                "description": "Xavier Tillman",
                                "price": 1.87,
                                "point": 10.5
                            }
                        ]
                    },
                    {
                        "key": "player_rebounds",
                        "last_update": "2024-01-24T09:54:52Z",
                        "outcomes": [
                            {
                                "name": "Over",
                                "description": "Bam Adebayo",
                                "price": 2.1,
                                "point": 11.5
                            },
                            {
                                "name": "Under",
                                "description": "Bam Adebayo",
                                "price": 1.71,
                                "point": 11.5
                            },
                            {
                                "name": "Over",
                                "description": "Jaren Jackson Jr.",
                                "price": 1.8,
                                "point": 5.5
                            },
                            {
                                "name": "Under",
                                "description": "Jaren Jackson Jr.",
                                "price": 1.95,
                                "point": 5.5
                            },
                            {
                                "name": "Over",
                                "description": "Luke Kennard",
                                "price": 2.0,
                                "point": 3.5
                            },
                            {
                                "name": "Under",
                                "description": "Luke Kennard",
                                "price": 1.77,
                                "point": 3.5
                            },
                            {
                                "name": "Over",
                                "description": "Tyler Herro",
                                "price": 1.91,
                                "point": 5.5
                            },
                            {
                                "name": "Under",
                                "description": "Tyler Herro",
                                "price": 1.83,
                                "point": 5.5
                            },
                            {
                                "name": "Over",
                                "description": "Vince Williams Jr.",
                                "price": 2.14,
                                "point": 7.5
                            },
                            {
                                "name": "Under",
                                "description": "Vince Williams Jr.",
                                "price": 1.69,
                                "point": 7.5
                            },
                            {
                                "name": "Over",
                                "description": "Xavier Tillman",
                                "price": 1.71,
                                "point": 6.5
                            },
                            {
                                "name": "Under",
                                "description": "Xavier Tillman",
                                "price": 2.1,
                                "point": 6.5
                            }
                        ]
                    }
                ]
            },
            {
                "key": "betonlineag",
                "title": "BetOnline.ag",
                "last_update": "2024-01-24T09:53:34Z",
                "markets": [
                    {
                        "key": "player_assists",
                        "last_update": "2024-01-24T09:55:48Z",
                        "outcomes": [
                            {
                                "name": "Under",
                                "description": "Xavier Tillman",
                                "price": 1.54,
                                "point": 3.5
                            },
                            {
                                "name": "Over",
                                "description": "Xavier Tillman",
                                "price": 2.41,
                                "point": 3.5
                            },
                            {
                                "name": "Under",
                                "description": "Luke Kennard",
                                "price": 1.82,
                                "point": 4.5
                            },
                            {
                                "name": "Over",
                                "description": "Luke Kennard",
                                "price": 1.94,
                                "point": 4.5
                            },
                            {
                                "name": "Over",
                                "description": "Tyler Herro",
                                "price": 1.98,
                                "point": 3.5
                            },
                            {
                                "name": "Under",
                                "description": "Tyler Herro",
                                "price": 1.79,
                                "point": 3.5
                            },
                            {
                                "name": "Under",
                                "description": "Jaren Jackson Jr.",
                                "price": 2.13,
                                "point": 2.5
                            },
                            {
                                "name": "Over",
                                "description": "Jaren Jackson Jr.",
                                "price": 1.68,
                                "point": 2.5
                            },
                            {
                                "name": "Under",
                                "description": "Bam Adebayo",
                                "price": 1.89,
                                "point": 4.5
                            },
                            {
                                "name": "Over",
                                "description": "Bam Adebayo",
                                "price": 1.87,
                                "point": 4.5
                            },
                            {
                                "name": "Over",
                                "description": "Vince Williams",
                                "price": 1.65,
                                "point": 3.5
                            },
                            {
                                "name": "Under",
                                "description": "Vince Williams",
                                "price": 2.19,
                                "point": 3.5
                            }
                        ]
                    },
                    {
                        "key": "player_points",
                        "last_update": "2024-01-24T09:55:48Z",
                        "outcomes": [
                            {
                                "name": "Over",
                                "description": "Xavier Tillman",
                                "price": 1.97,
                                "point": 10.5
                            },
                            {
                                "name": "Under",
                                "description": "Xavier Tillman",
                                "price": 1.8,
                                "point": 10.5
                            },
                            {
                                "name": "Under",
                                "description": "Tyler Herro",
                                "price": 1.98,
                                "point": 20.5
                            },
                            {
                                "name": "Over",
                                "description": "Tyler Herro",
                                "price": 1.79,
                                "point": 20.5
                            },
                            {
                                "name": "Over",
                                "description": "Vince Williams",
                                "price": 1.88,
                                "point": 12.5
                            },
                            {
                                "name": "Under",
                                "description": "Vince Williams",
                                "price": 1.88,
                                "point": 12.5
                            },
                            {
                                "name": "Over",
                                "description": "Luke Kennard",
                                "price": 1.91,
                                "point": 15.5
                            },
                            {
                                "name": "Under",
                                "description": "Luke Kennard",
                                "price": 1.85,
                                "point": 15.5
                            },
                            {
                                "name": "Over",
                                "description": "Jaren Jackson Jr.",
                                "price": 1.82,
                                "point": 24.5
                            },
                            {
                                "name": "Under",
                                "description": "Jaren Jackson Jr.",
                                "price": 1.94,
                                "point": 24.5
                            },
                            {
                                "name": "Over",
                                "description": "Bam Adebayo",
                                "price": 1.82,
                                "point": 20.5
                            },
                            {
                                "name": "Under",
                                "description": "Bam Adebayo",
                                "price": 1.94,
                                "point": 20.5
                            }
                        ]
                    },
                    {
                        "key": "player_rebounds",
                        "last_update": "2024-01-24T09:55:48Z",
                        "outcomes": [
                            {
                                "name": "Under",
                                "description": "Jaren Jackson Jr.",
                                "price": 1.95,
                                "point": 5.5
                            },
                            {
                                "name": "Over",
                                "description": "Jaren Jackson Jr.",
                                "price": 1.81,
                                "point": 5.5
                            },
                            {
                                "name": "Under",
                                "description": "Bam Adebayo",
                                "price": 1.71,
                                "point": 11.5
                            },
                            {
                                "name": "Over",
                                "description": "Bam Adebayo",
                                "price": 2.09,
                                "point": 11.5
                            },
                            {
                                "name": "Over",
                                "description": "Tyler Herro",
                                "price": 1.95,
                                "point": 5.5
                            },
                            {
                                "name": "Under",
                                "description": "Tyler Herro",
                                "price": 1.81,
                                "point": 5.5
                            },
                            {
                                "name": "Under",
                                "description": "Xavier Tillman",
                                "price": 2.04,
                                "point": 6.5
                            },
                            {
                                "name": "Over",
                                "description": "Xavier Tillman",
                                "price": 1.74,
                                "point": 6.5
                            },
                            {
                                "name": "Over",
                                "description": "Luke Kennard",
                                "price": 1.99,
                                "point": 3.5
                            },
                            {
                                "name": "Under",
                                "description": "Luke Kennard",
                                "price": 1.78,
                                "point": 3.5
                            },
                            {
                                "name": "Over",
                                "description": "Vince Williams",
                                "price": 2.1,
                                "point": 7.5
                            },
                            {
                                "name": "Under",
                                "description": "Vince Williams",
                                "price": 1.7,
                                "point": 7.5
                            }
                        ]
                    }
                ]
            },
            {
                "key": "williamhill_us",
                "title": "Caesars",
                "last_update": "2024-01-24T09:53:47Z",
                "markets": [
                    {
                        "key": "player_assists",
                        "last_update": "2024-01-24T09:55:21Z",
                        "outcomes": [
                            {
                                "name": "Over",
                                "description": "Xavier Tillman",
                                "price": 2.29,
                                "point": 3.5
                            },
                            {
                                "name": "Under",
                                "description": "Xavier Tillman",
                                "price": 1.56,
                                "point": 3.5
                            },
                            {
                                "name": "Over",
                                "description": "Tyler Herro",
                                "price": 1.96,
                                "point": 3.5
                            },
                            {
                                "name": "Under",
                                "description": "Tyler Herro",
                                "price": 1.76,
                                "point": 3.5
                            },
                            {
                                "name": "Over",
                                "description": "Bam Adebayo",
                                "price": 1.84,
                                "point": 4.5
                            },
                            {
                                "name": "Under",
                                "description": "Bam Adebayo",
                                "price": 1.87,
                                "point": 4.5
                            },
                            {
                                "name": "Over",
                                "description": "Luke Kennard",
                                "price": 1.93,
                                "point": 4.5
                            },
                            {
                                "name": "Under",
                                "description": "Luke Kennard",
                                "price": 1.79,
                                "point": 4.5
                            },
                            {
                                "name": "Over",
                                "description": "Jaren Jackson Jr.",
                                "price": 1.65,
                                "point": 2.5
                            },
                            {
                                "name": "Under",
                                "description": "Jaren Jackson Jr.",
                                "price": 2.12,
                                "point": 2.5
                            },
                            {
                                "name": "Over",
                                "description": "Vince Williams Jr.",
                                "price": 1.62,
                                "point": 3.5
                            },
                            {
                                "name": "Under",
                                "description": "Vince Williams Jr.",
                                "price": 2.16,
                                "point": 3.5
                            }
                        ]
                    },
                    {
                        "key": "player_points",
                        "last_update": "2024-01-24T09:55:21Z",
                        "outcomes": [
                            {
                                "name": "Over",
                                "description": "Xavier Tillman",
                                "price": 1.84,
                                "point": 10.5
                            },
                            {
                                "name": "Under",
                                "description": "Xavier Tillman",
                                "price": 1.87,
                                "point": 10.5
                            },
                            {
                                "name": "Over",
                                "description": "Tyler Herro",
                                "price": 1.79,
                                "point": 20.5
                            },
                            {
                                "name": "Under",
                                "description": "Tyler Herro",
                                "price": 1.93,
                                "point": 20.5
                            },
                            {
                                "name": "Over",
                                "description": "Jaren Jackson Jr.",
                                "price": 1.92,
                                "point": 25.5
                            },
                            {
                                "name": "Under",
                                "description": "Jaren Jackson Jr.",
                                "price": 1.8,
                                "point": 25.5
                            },
                            {
                                "name": "Over",
                                "description": "Luke Kennard",
                                "price": 1.92,
                                "point": 15.5
                            },
                            {
                                "name": "Under",
                                "description": "Luke Kennard",
                                "price": 1.8,
                                "point": 15.5
                            },
                            {
                                "name": "Over",
                                "description": "Bam Adebayo",
                                "price": 1.78,
                                "point": 20.5
                            },
                            {
                                "name": "Under",
                                "description": "Bam Adebayo",
                                "price": 1.94,
                                "point": 20.5
                            },
                            {
                                "name": "Over",
                                "description": "Vince Williams Jr.",
                                "price": 1.81,
                                "point": 12.5
                            },
                            {
                                "name": "Under",
                                "description": "Vince Williams Jr.",
                                "price": 1.9,
                                "point": 12.5
                            }
                        ]
                    },
                    {
                        "key": "player_rebounds",
                        "last_update": "2024-01-24T09:55:21Z",
                        "outcomes": [
                            {
                                "name": "Over",
                                "description": "Luke Kennard",
                                "price": 1.97,
                                "point": 3.5
                            },
                            {
                                "name": "Under",
                                "description": "Luke Kennard",
                                "price": 1.75,
                                "point": 3.5
                            },
                            {
                                "name": "Over",
                                "description": "Jaren Jackson Jr.",
                                "price": 1.78,
                                "point": 5.5
                            },
                            {
                                "name": "Under",
                                "description": "Jaren Jackson Jr.",
                                "price": 1.94,
                                "point": 5.5
                            },
                            {
                                "name": "Over",
                                "description": "Tyler Herro",
                                "price": 1.9,
                                "point": 5.5
                            },
                            {
                                "name": "Under",
                                "description": "Tyler Herro",
                                "price": 1.81,
                                "point": 5.5
                            },
                            {
                                "name": "Over",
                                "description": "Vince Williams Jr.",
                                "price": 2.08,
                                "point": 7.5
                            },
                            {
                                "name": "Under",
                                "description": "Vince Williams Jr.",
                                "price": 1.68,
                                "point": 7.5
                            },
                            {
                                "name": "Over",
                                "description": "Xavier Tillman",
                                "price": 1.66,
                                "point": 6.5
                            },
                            {
                                "name": "Under",
                                "description": "Xavier Tillman",
                                "price": 2.1,
                                "point": 6.5
                            },
                            {
                                "name": "Over",
                                "description": "Bam Adebayo",
                                "price": 2.04,
                                "point": 11.5
                            },
                            {
                                "name": "Under",
                                "description": "Bam Adebayo",
                                "price": 1.7,
                                "point": 11.5
                            }
                        ]
                    }
                ]
            },
            {
                "key": "pointsbetus",
                "title": "PointsBet (US)",
                "last_update": "2024-01-24T09:55:24Z",
                "markets": [
                    {
                        "key": "player_assists",
                        "last_update": "2024-01-24T09:54:01Z",
                        "outcomes": [
                            {
                                "name": "Over",
                                "description": "Bam Adebayo",
                                "price": 1.8,
                                "point": 4.5
                            },
                            {
                                "name": "Under",
                                "description": "Bam Adebayo",
                                "price": 1.95,
                                "point": 4.5
                            },
                            {
                                "name": "Over",
                                "description": "Jaren Jackson Jr.",
                                "price": 1.71,
                                "point": 2.5
                            },
                            {
                                "name": "Under",
                                "description": "Jaren Jackson Jr.",
                                "price": 2.05,
                                "point": 2.5
                            },
                            {
                                "name": "Over",
                                "description": "Luke Kennard",
                                "price": 1.87,
                                "point": 4.5
                            },
                            {
                                "name": "Under",
                                "description": "Luke Kennard",
                                "price": 1.87,
                                "point": 4.5
                            },
                            {
                                "name": "Over",
                                "description": "Tyler Herro",
                                "price": 1.95,
                                "point": 3.5
                            },
                            {
                                "name": "Under",
                                "description": "Tyler Herro",
                                "price": 1.8,
                                "point": 3.5
                            },
                            {
                                "name": "Over",
                                "description": "Vince Williams Jr.",
                                "price": 1.62,
                                "point": 3.5
                            },
                            {
                                "name": "Under",
                                "description": "Vince Williams Jr.",
                                "price": 2.2,
                                "point": 3.5
                            },
                            {
                                "name": "Over",
                                "description": "Xavier Tillman",
                                "price": 1.59,
                                "point": 2.5
                            },
                            {
                                "name": "Under",
                                "description": "Xavier Tillman",
                                "price": 2.3,
                                "point": 2.5
                            }
                        ]
                    },
                    {
                        "key": "player_points",
                        "last_update": "2024-01-24T09:54:01Z",
                        "outcomes": [
                            {
                                "name": "Over",
                                "description": "Bam Adebayo",
                                "price": 1.83,
                                "point": 20.5
                            },
                            {
                                "name": "Under",
                                "description": "Bam Adebayo",
                                "price": 1.91,
                                "point": 20.5
                            },
                            {
                                "name": "Over",
                                "description": "Jaren Jackson Jr.",
                                "price": 1.95,
                                "point": 26.5
                            },
                            {
                                "name": "Under",
                                "description": "Jaren Jackson Jr.",
                                "price": 1.8,
                                "point": 26.5
                            },
                            {
                                "name": "Over",
                                "description": "Luke Kennard",
                                "price": 1.95,
                                "point": 15.5
                            },
                            {
                                "name": "Under",
                                "description": "Luke Kennard",
                                "price": 1.8,
                                "point": 15.5
                            },
                            {
                                "name": "Over",
                                "description": "Tyler Herro",
                                "price": 1.87,
                                "point": 21.5
                            },
                            {
                                "name": "Under",
                                "description": "Tyler Herro",
                                "price": 1.87,
                                "point": 21.5
                            },
                            {
                                "name": "Over",
                                "description": "Vince Williams Jr.",
                                "price": 1.87,
                                "point": 12.5
                            },
                            {
                                "name": "Under",
                                "description": "Vince Williams Jr.",
                                "price": 1.87,
                                "point": 12.5
                            },
                            {
                                "name": "Over",
                                "description": "Xavier Tillman",
                                "price": 1.87,
                                "point": 10.5
                            },
                            {
                                "name": "Under",
                                "description": "Xavier Tillman",
                                "price": 1.87,
                                "point": 10.5
                            }
                        ]
                    },
                    {
                        "key": "player_rebounds",
                        "last_update": "2024-01-24T09:54:01Z",
                        "outcomes": [
                            {
                                "name": "Over",
                                "description": "Bam Adebayo",
                                "price": 2.1,
                                "point": 11.5
                            },
                            {
                                "name": "Under",
                                "description": "Bam Adebayo",
                                "price": 1.69,
                                "point": 11.5
                            },
                            {
                                "name": "Over",
                                "description": "Jaren Jackson Jr.",
                                "price": 1.8,
                                "point": 5.5
                            },
                            {
                                "name": "Under",
                                "description": "Jaren Jackson Jr.",
                                "price": 1.95,
                                "point": 5.5
                            },
                            {
                                "name": "Over",
                                "description": "Luke Kennard",
                                "price": 1.95,
                                "point": 3.5
                            },
                            {
                                "name": "Under",
                                "description": "Luke Kennard",
                                "price": 1.8,
                                "point": 3.5
                            },
                            {
                                "name": "Over",
                                "description": "Tyler Herro",
                                "price": 1.87,
                                "point": 5.5
                            },
                            {
                                "name": "Under",
                                "description": "Tyler Herro",
                                "price": 1.87,
                                "point": 5.5
                            },
                            {
                                "name": "Over",
                                "description": "Vince Williams Jr.",
                                "price": 2.15,
                                "point": 7.5
                            },
                            {
                                "name": "Under",
                                "description": "Vince Williams Jr.",
                                "price": 1.67,
                                "point": 7.5
                            },
                            {
                                "name": "Over",
                                "description": "Xavier Tillman",
                                "price": 1.69,
                                "point": 6.5
                            },
                            {
                                "name": "Under",
                                "description": "Xavier Tillman",
                                "price": 2.1,
                                "point": 6.5
                            }
                        ]
                    }
                ]
            },
            {
                "key": "fanduel",
                "title": "FanDuel",
                "last_update": "2024-01-24T09:54:54Z",
                "markets": [
                    {
                        "key": "player_assists",
                        "last_update": "2024-01-24T09:53:58Z",
                        "outcomes": [
                            {
                                "name": "Over",
                                "description": "Bam Adebayo",
                                "price": 1.88,
                                "point": 4.5
                            },
                            {
                                "name": "Under",
                                "description": "Bam Adebayo",
                                "price": 1.88,
                                "point": 4.5
                            },
                            {
                                "name": "Over",
                                "description": "Luke Kennard",
                                "price": 1.9,
                                "point": 4.5
                            },
                            {
                                "name": "Under",
                                "description": "Luke Kennard",
                                "price": 1.87,
                                "point": 4.5
                            },
                            {
                                "name": "Over",
                                "description": "Jaren Jackson Jr.",
                                "price": 1.7,
                                "point": 2.5
                            },
                            {
                                "name": "Under",
                                "description": "Jaren Jackson Jr.",
                                "price": 2.12,
                                "point": 2.5
                            },
                            {
                                "name": "Over",
                                "description": "Xavier Tillman",
                                "price": 1.56,
                                "point": 2.5
                            },
                            {
                                "name": "Under",
                                "description": "Xavier Tillman",
                                "price": 2.38,
                                "point": 2.5
                            },
                            {
                                "name": "Over",
                                "description": "Vince Williams Jr.",
                                "price": 1.68,
                                "point": 3.5
                            },
                            {
                                "name": "Under",
                                "description": "Vince Williams Jr.",
                                "price": 2.16,
                                "point": 3.5
                            },
                            {
                                "name": "Over",
                                "description": "Tyler Herro",
                                "price": 1.88,
                                "point": 3.5
                            },
                            {
                                "name": "Under",
                                "description": "Tyler Herro",
                                "price": 1.88,
                                "point": 3.5
                            }
                        ]
                    },
                    {
                        "key": "player_points",
                        "last_update": "2024-01-24T09:53:58Z",
                        "outcomes": [
                            {
                                "name": "Over",
                                "description": "Jaren Jackson Jr.",
                                "price": 1.8,
                                "point": 24.5
                            },
                            {
                                "name": "Under",
                                "description": "Jaren Jackson Jr.",
                                "price": 1.98,
                                "point": 24.5
                            },
                            {
                                "name": "Over",
                                "description": "Luke Kennard",
                                "price": 1.9,
                                "point": 15.5
                            },
                            {
                                "name": "Under",
                                "description": "Luke Kennard",
                                "price": 1.87,
                                "point": 15.5
                            },
                            {
                                "name": "Over",
                                "description": "Tyler Herro",
                                "price": 1.87,
                                "point": 20.5
                            },
                            {
                                "name": "Under",
                                "description": "Tyler Herro",
                                "price": 1.9,
                                "point": 20.5
                            },
                            {
                                "name": "Over",
                                "description": "Bam Adebayo",
                                "price": 1.93,
                                "point": 21.5
                            },
                            {
                                "name": "Under",
                                "description": "Bam Adebayo",
                                "price": 1.85,
                                "point": 21.5
                            },
                            {
                                "name": "Over",
                                "description": "Xavier Tillman",
                                "price": 2.0,
                                "point": 10.5
                            },
                            {
                                "name": "Under",
                                "description": "Xavier Tillman",
                                "price": 1.78,
                                "point": 10.5
                            },
                            {
                                "name": "Over",
                                "description": "Vince Williams Jr.",
                                "price": 1.88,
                                "point": 12.5
                            },
                            {
                                "name": "Under",
                                "description": "Vince Williams Jr.",
                                "price": 1.88,
                                "point": 12.5
                            }
                        ]
                    },
                    {
                        "key": "player_rebounds",
                        "last_update": "2024-01-24T09:53:58Z",
                        "outcomes": [
                            {
                                "name": "Over",
                                "description": "Vince Williams Jr.",
                                "price": 2.08,
                                "point": 7.5
                            },
                            {
                                "name": "Under",
                                "description": "Vince Williams Jr.",
                                "price": 1.72,
                                "point": 7.5
                            },
                            {
                                "name": "Over",
                                "description": "Bam Adebayo",
                                "price": 1.98,
                                "point": 11.5
                            },
                            {
                                "name": "Under",
                                "description": "Bam Adebayo",
                                "price": 1.78,
                                "point": 11.5
                            },
                            {
                                "name": "Over",
                                "description": "Xavier Tillman",
                                "price": 1.78,
                                "point": 6.5
                            },
                            {
                                "name": "Under",
                                "description": "Xavier Tillman",
                                "price": 2.0,
                                "point": 6.5
                            },
                            {
                                "name": "Over",
                                "description": "Tyler Herro",
                                "price": 2.02,
                                "point": 5.5
                            },
                            {
                                "name": "Under",
                                "description": "Tyler Herro",
                                "price": 1.77,
                                "point": 5.5
                            },
                            {
                                "name": "Over",
                                "description": "Luke Kennard",
                                "price": 2.0,
                                "point": 3.5
                            },
                            {
                                "name": "Under",
                                "description": "Luke Kennard",
                                "price": 1.78,
                                "point": 3.5
                            },
                            {
                                "name": "Over",
                                "description": "Jaren Jackson Jr.",
                                "price": 1.88,
                                "point": 5.5
                            },
                            {
                                "name": "Under",
                                "description": "Jaren Jackson Jr.",
                                "price": 1.88,
                                "point": 5.5
                            }
                        ]
                    }
                ]
            },
            {
                "key": "betmgm",
                "title": "BetMGM",
                "last_update": "2024-01-24T09:54:05Z",
                "markets": [
                    {
                        "key": "player_assists",
                        "last_update": "2024-01-24T09:55:34Z",
                        "outcomes": [
                            {
                                "name": "Over",
                                "description": "Luke Kennard",
                                "price": 1.91,
                                "point": 4.5
                            },
                            {
                                "name": "Under",
                                "description": "Luke Kennard",
                                "price": 1.83,
                                "point": 4.5
                            },
                            {
                                "name": "Over",
                                "description": "Bam Adebayo",
                                "price": 1.87,
                                "point": 4.5
                            },
                            {
                                "name": "Under",
                                "description": "Bam Adebayo",
                                "price": 1.87,
                                "point": 4.5
                            },
                            {
                                "name": "Over",
                                "description": "Tyler Herro",
                                "price": 1.95,
                                "point": 3.5
                            },
                            {
                                "name": "Under",
                                "description": "Tyler Herro",
                                "price": 1.77,
                                "point": 3.5
                            },
                            {
                                "name": "Over",
                                "description": "Jaren Jackson Jr.",
                                "price": 1.69,
                                "point": 2.5
                            },
                            {
                                "name": "Under",
                                "description": "Jaren Jackson Jr.",
                                "price": 2.1,
                                "point": 2.5
                            },
                            {
                                "name": "Over",
                                "description": "Xavier Tillman",
                                "price": 2.35,
                                "point": 3.5
                            },
                            {
                                "name": "Under",
                                "description": "Xavier Tillman",
                                "price": 1.54,
                                "point": 3.5
                            },
                            {
                                "name": "Over",
                                "description": "Vince Williams Jr",
                                "price": 1.62,
                                "point": 3.5
                            },
                            {
                                "name": "Under",
                                "description": "Vince Williams Jr",
                                "price": 2.2,
                                "point": 3.5
                            }
                        ]
                    },
                    {
                        "key": "player_points",
                        "last_update": "2024-01-24T09:55:34Z",
                        "outcomes": [
                            {
                                "name": "Over",
                                "description": "Luke Kennard",
                                "price": 1.91,
                                "point": 15.5
                            },
                            {
                                "name": "Under",
                                "description": "Luke Kennard",
                                "price": 1.83,
                                "point": 15.5
                            },
                            {
                                "name": "Over",
                                "description": "Tyler Herro",
                                "price": 1.8,
                                "point": 20.5
                            },
                            {
                                "name": "Under",
                                "description": "Tyler Herro",
                                "price": 1.95,
                                "point": 20.5
                            },
                            {
                                "name": "Over",
                                "description": "Jaren Jackson Jr.",
                                "price": 1.95,
                                "point": 25.5
                            },
                            {
                                "name": "Under",
                                "description": "Jaren Jackson Jr.",
                                "price": 1.8,
                                "point": 25.5
                            },
                            {
                                "name": "Over",
                                "description": "Xavier Tillman",
                                "price": 1.87,
                                "point": 10.5
                            },
                            {
                                "name": "Under",
                                "description": "Xavier Tillman",
                                "price": 1.87,
                                "point": 10.5
                            },
                            {
                                "name": "Over",
                                "description": "Vince Williams Jr",
                                "price": 1.83,
                                "point": 12.5
                            },
                            {
                                "name": "Under",
                                "description": "Vince Williams Jr",
                                "price": 1.91,
                                "point": 12.5
                            },
                            {
                                "name": "Over",
                                "description": "Bam Adebayo",
                                "price": 1.77,
                                "point": 20.5
                            },
                            {
                                "name": "Under",
                                "description": "Bam Adebayo",
                                "price": 1.95,
                                "point": 20.5
                            }
                        ]
                    },
                    {
                        "key": "player_rebounds",
                        "last_update": "2024-01-24T09:55:34Z",
                        "outcomes": [
                            {
                                "name": "Over",
                                "description": "Luke Kennard",
                                "price": 2.0,
                                "point": 3.5
                            },
                            {
                                "name": "Under",
                                "description": "Luke Kennard",
                                "price": 1.77,
                                "point": 3.5
                            },
                            {
                                "name": "Over",
                                "description": "Bam Adebayo",
                                "price": 2.05,
                                "point": 11.5
                            },
                            {
                                "name": "Under",
                                "description": "Bam Adebayo",
                                "price": 1.69,
                                "point": 11.5
                            },
                            {
                                "name": "Over",
                                "description": "Tyler Herro",
                                "price": 1.91,
                                "point": 5.5
                            },
                            {
                                "name": "Under",
                                "description": "Tyler Herro",
                                "price": 1.83,
                                "point": 5.5
                            },
                            {
                                "name": "Over",
                                "description": "Jaren Jackson Jr.",
                                "price": 1.8,
                                "point": 5.5
                            },
                            {
                                "name": "Under",
                                "description": "Jaren Jackson Jr.",
                                "price": 1.95,
                                "point": 5.5
                            },
                            {
                                "name": "Over",
                                "description": "Xavier Tillman",
                                "price": 1.69,
                                "point": 6.5
                            },
                            {
                                "name": "Under",
                                "description": "Xavier Tillman",
                                "price": 2.1,
                                "point": 6.5
                            },
                            {
                                "name": "Over",
                                "description": "Vince Williams Jr",
                                "price": 2.1,
                                "point": 7.5
                            },
                            {
                                "name": "Under",
                                "description": "Vince Williams Jr",
                                "price": 1.69,
                                "point": 7.5
                            }
                        ]
                    }
                ]
            },
            {
                "key": "bovada",
                "title": "Bovada",
                "last_update": "2024-01-24T09:55:12Z",
                "markets": [
                    {
                        "key": "player_assists",
                        "last_update": "2024-01-24T09:55:52Z",
                        "outcomes": [
                            {
                                "name": "Over",
                                "description": "Bam Adebayo",
                                "price": 1.83,
                                "point": 4.5
                            },
                            {
                                "name": "Under",
                                "description": "Bam Adebayo",
                                "price": 1.91,
                                "point": 4.5
                            },
                            {
                                "name": "Over",
                                "description": "Jaren Jackson Jr.",
                                "price": 1.69,
                                "point": 2.5
                            },
                            {
                                "name": "Under",
                                "description": "Jaren Jackson Jr.",
                                "price": 2.1,
                                "point": 2.5
                            },
                            {
                                "name": "Over",
                                "description": "Luke Kennard",
                                "price": 1.91,
                                "point": 4.5
                            },
                            {
                                "name": "Under",
                                "description": "Luke Kennard",
                                "price": 1.83,
                                "point": 4.5
                            },
                            {
                                "name": "Over",
                                "description": "Tyler Herro",
                                "price": 1.95,
                                "point": 3.5
                            },
                            {
                                "name": "Under",
                                "description": "Tyler Herro",
                                "price": 1.8,
                                "point": 3.5
                            },
                            {
                                "name": "Over",
                                "description": "Vince Williams Jr.",
                                "price": 1.62,
                                "point": 3.5
                            },
                            {
                                "name": "Under",
                                "description": "Vince Williams Jr.",
                                "price": 2.2,
                                "point": 3.5
                            },
                            {
                                "name": "Over",
                                "description": "Xavier Tillman Sr",
                                "price": 2.35,
                                "point": 3.5
                            },
                            {
                                "name": "Under",
                                "description": "Xavier Tillman Sr",
                                "price": 1.56,
                                "point": 3.5
                            }
                        ]
                    },
                    {
                        "key": "player_points",
                        "last_update": "2024-01-24T09:55:52Z",
                        "outcomes": [
                            {
                                "name": "Over",
                                "description": "Xavier Tillman Sr",
                                "price": 2.05,
                                "point": 10.5
                            },
                            {
                                "name": "Under",
                                "description": "Xavier Tillman Sr",
                                "price": 1.74,
                                "point": 10.5
                            }
                        ]
                    },
                    {
                        "key": "player_rebounds",
                        "last_update": "2024-01-24T09:55:52Z",
                        "outcomes": [
                            {
                                "name": "Over",
                                "description": "Bam Adebayo",
                                "price": 2.1,
                                "point": 11.5
                            },
                            {
                                "name": "Under",
                                "description": "Bam Adebayo",
                                "price": 1.69,
                                "point": 11.5
                            },
                            {
                                "name": "Over",
                                "description": "Jaren Jackson Jr.",
                                "price": 1.8,
                                "point": 5.5
                            },
                            {
                                "name": "Under",
                                "description": "Jaren Jackson Jr.",
                                "price": 1.95,
                                "point": 5.5
                            },
                            {
                                "name": "Over",
                                "description": "Luke Kennard",
                                "price": 2.0,
                                "point": 3.5
                            },
                            {
                                "name": "Under",
                                "description": "Luke Kennard",
                                "price": 1.77,
                                "point": 3.5
                            },
                            {
                                "name": "Over",
                                "description": "Tyler Herro",
                                "price": 1.91,
                                "point": 5.5
                            },
                            {
                                "name": "Under",
                                "description": "Tyler Herro",
                                "price": 1.83,
                                "point": 5.5
                            },
                            {
                                "name": "Over",
                                "description": "Vince Williams Jr.",
                                "price": 2.1,
                                "point": 7.5
                            },
                            {
                                "name": "Under",
                                "description": "Vince Williams Jr.",
                                "price": 1.69,
                                "point": 7.5
                            },
                            {
                                "name": "Over",
                                "description": "Xavier Tillman Sr",
                                "price": 1.69,
                                "point": 6.5
                            },
                            {
                                "name": "Under",
                                "description": "Xavier Tillman Sr",
                                "price": 2.1,
                                "point": 6.5
                            }
                        ]
                    }
                ]
            }
        ]
    }
}