{
    "timestamp": "2023-11-26T09:55:39Z",
    "previous_timestamp": "2023-11-26T09:50:38Z",
    "next_timestamp": "2023-11-26T10:00:39Z",
    "data": {
        "id": "3a7425b0f8487a723856a7c913c9f421",
        "sport_key": "basketball_nba",
        "sport_title": "NBA",
        "commence_time": "2023-11-26T23:10:00Z",
        "home_team": "Boston Celtics",
        "away_team": "Atlanta Hawks",
        "bookmakers": [
            {
                "key": "draftkings",
                "title": "DraftKings",
                "last_update": "2023-11-26T09:54:59Z",
                "markets": [
                    {
                        "key": "player_assists",
                        "last_update": "2023-11-26T09:53:58Z",
                        "outcomes": [
                            {
                                "name": "Over",
                                "description": "Jaylen Brown",
                                "price": 2.1,
                                "point": 3.5
                            },
                            {
                                "name": "Under",
                                "description": "Jaylen Brown",
                                "price": 1.71,
                                "point": 3.5
                            },
                            {
                                "name": "Over",
                                "description": "Jayson Tatum",
                                "price": 2.1,
                                "point": 4.5
                            },
                            {
                                "name": "Under",
                                "description": "Jayson Tatum",
                                "price": 1.71,
                                "point": 4.5
                            },
                            {
                                "name": "Over",
                                "description": "Trae Young",
                                "price": 1.74,
                                "point": 9.5
                            },
                            {
                                "name": "Under",
                                "description": "Trae Young",
                                "price": 2.05,
                                "point": 9.5
                            }
                        ]
                    },
                    {
                        "key": "player_points",
                        "last_update": "2023-11-26T09:53:58Z",
                        "outcomes": [
                            {
                                "name": "Over",
                                "description": "Jaylen Brown",
                                "price": 1.83,
                                "point": 24.5
                            },
                            {
                                "name": "Under",
                                "description": "Jaylen Brown",
                                "price": 1.95,
                                "point": 24.5
                            },
                            {
                                "name": "Over",
                                "description": "Jayson Tatum",
                                "price": 1.87,
                                "point": 29.5
                            },
                            {
                                "name": "Under",
                                "description": "Jayson Tatum",
                                "price": 1.91,
                                "point": 29.5
                            },
                            {
                                "name": "Over",
                                "description": "Trae Young",
                                "price": 1.91,
                                "point": 24.5
                            },
                            {
                                "name": "Under",
                                "description": "Trae Young",
                                "price": 1.87,
                                "point": 24.5
                            }
                        ]
                    },
                    {
                        "key": "player_rebounds",
                        "last_update": "2023-11-26T09:53:58Z",
                        "outcomes": [
                            {
                                "name": "Over",
                                "description": "Jaylen Brown",
                                "price": 2.1,
                                "point": 5.5
                            },
                            {
                                "name": "Under",
                                "description": "Jaylen Brown",
                                "price": 1.69,
                                "point": 5.5
                            },
                            {
                                "name": "Over",
                                "description": "Jayson Tatum",
                                "price": 1.87,
                                "point": 9.5
                            },
                            {
                                "name": "Under",
                                "description": "Jayson Tatum",
                                "price": 1.91,
                                "point": 9.5
                            },
                            {
                                "name": "Over",
                                "description": "Trae Young",
                                "price": 2.4,
                                "point": 3.5
                            },
                            {
                                "name": "Under",
                                "description": "Trae Young",
                                "price": 1.56,
                                "point": 3.5
                            }
                        ]
                    }
                ]
            },
            {
                "key": "fanduel",
                "title": "FanDuel",
                "last_update": "2023-11-26T09:53:37Z",
                "markets": [
                    {
                        "key": "player_assists",
                        "last_update": "2023-11-26T09:55:49Z",
                        "outcomes": [
                            {
                                "name": "Over",
                                "description": "Trae Young",
                                "price": 1.71,
                                "point": 9.5
                            },
                            {
                                "name": "Under",
                                "description": "Trae Young",
                                "price": 2.1,
                                "point": 9.5
                            },
                            {
                                "name": "Over",
                                "description": "Jayson Tatum",
                                "price": 2.22,
                                "point": 4.5
                            },
                            {
                                "name": "Under",
                                "description": "Jayson Tatum",
                                "price": 1.64,
                                "point": 4.5
                            },
                            {
                                "name": "Over",
                                "description": "Jaylen Brown",
                                "price": 1.96,
                                "point": 3.5
                            },
                            {
                                "name": "Under",
                                "description": "Jaylen Brown",
                                "price": 1.82,
                                "point": 3.5
                            },
                            {
                                "name": "Over",
                                "description": "Dejounte Murray",
                                "price": 2.12,
                                "point": 5.5
                            },
                            {
                                "name": "Under",
                                "description": "Dejounte Murray",
                                "price": 1.7,
                                "point": 5.5
                            }
                        ]
                    },
                    {
                        "key": "player_points",
                        "last_update": "2023-11-26T09:55:49Z",
                        "outcomes": [
                            {
                                "name": "Over",
                                "description": "Jaylen Brown",
                                "price": 1.93,
                                "point": 24.5
                            },
                            {
                                "name": "Under",
                                "description": "Jaylen Brown",
                                "price": 1.85,
                                "point": 24.5
                            },
                            {
                                "name": "Over",
                                "description": "Jayson Tatum",
                                "price": 1.82,
                                "point": 29.5
                            },
                            {
                                "name": "Under",
                                "description": "Jayson Tatum",
                                "price": 1.96,
                                "point": 29.5
                            },
                            {
                                "name": "Over",
                                "description": "Trae Young",
                                "price": 1.83,
                                "point": 24.5
                            },
                            {
                                "name": "Under",
                                "description": "Trae Young",
                                "price": 1.94,
                                "point": 24.5
                            },
                            {
                                "name": "Over",
                                "description": "Dejounte Murray",
                                "price": 1.82,
                                "point": 19.5
                            },
                            {
                                "name": "Under",
                                "description": "Dejounte Murray",
                                "price": 1.96,
                                "point": 19.5
                            }
                        ]
                    },
                    {
                        "key": "player_rebounds",
                        "last_update": "2023-11-26T09:55:49Z",
                        "outcomes": [
                            {
                                "name": "Over",
                                "description": "Dejounte Murray",
                                "price": 2.08,
                                "point": 4.5
                            },
                            {
                                "name": "Under",
                                "description": "Dejounte Murray",
                                "price": 1.72,
                                "point": 4.5
                            },
                            {
                                "name": "Over",
                                "description": "Jayson Tatum",
                                "price": 1.9,
                                "point": 9.5
                            },
                            {
                                "name": "Under",
                                "description": "Jayson Tatum",
                                "price": 1.87,
                                "point": 9.5
                            },
                            {
                                "name": "Over",
                                "description": "Trae Young",
                                "price": 1.63,
                                "point": 2.5
                            },
                            {
                                "name": "Under",
                                "description": "Trae Young",
                                "price": 2.24,
                                "point": 2.5
                            },
                            {
                                "name": "Over",
                                "description": "Jaylen Brown",
                                "price": 1.68,
                                "point": 4.5
                            },
                            {
                                "name": "Under",
                                "description": "Jaylen Brown",
                                "price": 2.16,
                                "point": 4.5
                            }
                        ]
                    }
                ]
            },
            {
                "key": "pointsbetus",
                "title": "PointsBet (US)",
                "last_update": "2023-11-26T09:54:59Z",
                "markets": [
                    {
                        "key": "player_assists",
                        "last_update": "2023-11-26T09:54:25Z",
                        "outcomes": [
                            {
                                "name": "Over",
                                "description": "Jaylen Brown",
                                "price": 2.0,
                                "point": 3.5
                            },
                            {
                                "name": "Under",
                                "description": "Jaylen Brown",
                                "price": 1.77,
                                "point": 3.5
                            },
                            {
                                "name": "Over",
                                "description": "Jayson Tatum",
                                "price": 2.1,
                                "point": 4.5
                            },
                            {
                                "name": "Under",
                                "description": "Jayson Tatum",
                                "price": 1.69,
                                "point": 4.5
                            },
                            {
                                "name": "Over",
                                "description": "Trae Young",
                                "price": 1.71,
                                "point": 9.5
                            },
                            {
                                "name": "Under",
                                "description": "Trae Young",
                                "price": 2.05,
                                "point": 9.5
                            }
                        ]
                    },
                    {
                        "key": "player_points",
                        "last_update": "2023-11-26T09:54:25Z",
                        "outcomes": [
                            {
                                "name": "Over",
                                "description": "Jaylen Brown",
                                "price": 1.83,
                                "point": 24.5
                            },
                            {
                                "name": "Under",
                                "description": "Jaylen Brown",
                                "price": 1.91,
                                "point": 24.5
                            },
                            {
                                "name": "Over",
                                "description": "Jayson Tatum",
                                "price": 1.87,
                                "point": 29.5
                            },
                            {
                                "name": "Under",
                                "description": "Jayson Tatum",
                                "price": 1.87,
                                "point": 29.5
                            },
                            {
                                "name": "Over",
                                "description": "Trae Young",
                                "price": 1.87,
                                "point": 24.5
                            },
                            {
                                "name": "Under",
                                "description": "Trae Young",
                                "price": 1.87,
                                "point": 24.5
                            }
                        ]
                    },
                    {
                        "key": "player_rebounds",
                        "last_update": "2023-11-26T09:54:25Z",
                        "outcomes": [
                            {
                                "name": "Over",
                                "description": "Jaylen Brown",
                                "price": 2.1,
                                "point": 5.5
                            },
                            {
                                "name": "Under",
                                "description": "Jaylen Brown",
                                "price": 1.69,
                                "point": 5.5
                            },
                            {
                                "name": "Over",
                                "description": "Jayson Tatum",
                                "price": 1.83,
                                "point": 9.5
                            },
                            {
                                "name": "Under",
                                "description": "Jayson Tatum",
                                "price": 1.91,
                                "point": 9.5
                            },
                            {
                                "name": "Over",
                                "description": "Trae Young",
                                "price": 1.57,
                                "point": 2.5
                            },
                            {
                                "name": "Under",
                                "description": "Trae Young",
                                "price": 2.35,
                                "point": 2.5
                            }
                        ]
                    }
                ]
            },
            {
                "key": "williamhill_us",
                "title": "Caesars",
                "last_update": "2023-11-26T09:53:06Z",
                "markets": [
                    {
                        "key": "player_assists",
                        "last_update": "2023-11-26T09:54:42Z",
                        "outcomes": [
                            {
                                "name": "Over",
                                "description": "Jayson Tatum",
                                "price": 1.99,
                                "point": 4.5
                            },
                            {
                                "name": "Under",
                                "description": "Jayson Tatum",
                                "price": 1.74,
                                "point": 4.5
                            },
                            {
                                "name": "Over",
                                "description": "Trae Young",
                                "price": 1.72,
                                "point": 9.5
                            },
                            {
                                "name": "Under",
                                "description": "Trae Young",
                                "price": 2.02,
                                "point": 9.5
                            },
                            {
                                "name": "Over",
                                "description": "Jaylen Brown",
                                "price": 2.04,
                                "point": 3.5
                            },
                            {
                                "name": "Under",
                                "description": "Jaylen Brown",
                                "price": 1.7,
                                "point": 3.5
                            }
                        ]
                    },
                    {
                        "key": "player_points",
                        "last_update": "2023-11-26T09:54:42Z",
                        "outcomes": [
                            {
                                "name": "Over",
                                "description": "Jaylen Brown",
                                "price": 1.83,
                                "point": 24.5
                            },
                            {
                                "name": "Under",
                                "description": "Jaylen Brown",
                                "price": 1.88,
                                "point": 24.5
                            },
                            {
                                "name": "Over",
                                "description": "Jayson Tatum",
                                "price": 1.81,
                                "point": 29.5
                            },
                            {
                                "name": "Under",
                                "description": "Jayson Tatum",
                                "price": 1.9,
                                "point": 29.5
                            },
                            {
                                "name": "Over",
                                "description": "Trae Young",
                                "price": 1.85,
                                "point": 24.5
                            },
                            {
                                "name": "Under",
                                "description": "Trae Young",
                                "price": 1.85,
                                "point": 24.5
                            }
                        ]
                    },
                    {
                        "key": "player_rebounds",
                        "last_update": "2023-11-26T09:54:42Z",
                        "outcomes": [
                            {
                                "name": "Over",
                                "description": "Jayson Tatum",
                                "price": 1.83,
                                "point": 9.5
                            },
                            {
                                "name": "Under",
                                "description": "Jayson Tatum",
                                "price": 1.88,
                                "point": 9.5
                            },
                            {
                                "name": "Over",
                                "description": "Jaylen Brown",
                                "price": 2.04,
                                "point": 5.5
                            },
                            {
                                "name": "Under",
                                "description": "Jaylen Brown",
                                "price": 1.7,
                                "point": 5.5
                            },
                            {
                                "name": "Over",
                                "description": "Trae Young",
                                "price": 2.33,
                                "point": 3.5
                            },
                            {
                                "name": "Under",
                                "description": "Trae Young",
                                "price": 1.54,
                                "point": 3.5
                            }
                        ]
                    }
                ]
            },
            {
                "key": "bovada",
                "title": "Bovada",
                "last_update": "2023-11-26T09:54:46Z",
                "markets": [
                    {
                        "key": "player_assists",
                        "last_update": "2023-11-26T09:51:43Z",
                        "outcomes": [
                            {
                                "name": "Over",
                                "description": "Jaylen Brown",
                                "price": 2.1,
                                "point": 3.5
                            },
                            {
                                "name": "Under",
                                "description": "Jaylen Brown",
                                "price": 1.69,
                                "point": 3.5
                            },
                            {
                                "name": "Over",
                                "description": "Jayson Tatum",
                                "price": 2.1,
                                "point": 4.5
                            },
                            {
                                "name": "Under",
                                "description": "Jayson Tatum",
                                "price": 1.69,
                                "point": 4.5
                            },
                            {
                                "name": "Over",
                                "description": "Murray Dejounte",
                                "price": 2.1,
                                "point": 5.5
                            },
                            {
                                "name": "Under",
                                "description": "Murray Dejounte",
                                "price": 1.69,
                                "point": 5.5
                            },
                            {
                                "name": "Over",
                                "description": "Trae Young",
                                "price": 1.74,
                                "point": 9.5
                            },
                            {
                                "name": "Under",
                                "description": "Trae Young",
                                "price": 2.05,
                                "point": 9.5
                            }
                        ]
                    },
                    {
                        "key": "player_points",
                        "last_update": "2023-11-26T09:51:43Z",
                        "outcomes": [
                            {
                                "name": "Over",
                                "description": "Atl Hawks Alternate Total",
                                "price": 3.4,
                                "point": 121.5
                            },
                            {
                                "name": "Over",
                                "description": "Jaylen Brown",
                                "price": 1.8,
                                "point": 24.5
                            },
                            {
                                "name": "Under",
                                "description": "Jaylen Brown",
                                "price": 1.95,
                                "point": 24.5
                            },
                            {
                                "name": "Over",
                                "description": "Jayson Tatum",
                                "price": 1.83,
                                "point": 29.5
                            },
                            {
                                "name": "Under",
                                "description": "Jayson Tatum",
                                "price": 1.91,
                                "point": 29.5
                            },
                            {
                                "name": "Over",
                                "description": "Murray Dejounte",
                                "price": 1.74,
                                "point": 19.5
                            },
                            {
                                "name": "Under",
                                "description": "Murray Dejounte",
                                "price": 2.05,
                                "point": 19.5
                            },
                            {
                                "name": "Over",
                                "description": "Trae Young",
                                "price": 1.91,
                                "point": 24.5
                            },
                            {
                                "name": "Under",
                                "description": "Trae Young",
                                "price": 1.83,
                                "point": 24.5
                            }
                        ]
                    },
                    {
                        "key": "player_rebounds",
                        "last_update": "2023-11-26T09:51:43Z",
                        "outcomes": [
                            {
                                "name": "Over",
                                "description": "Jaylen Brown",
                                "price": 1.69,
                                "point": 4.5
                            },
                            {
                                "name": "Under",
                                "description": "Jaylen Brown",
                                "price": 2.1,
                                "point": 4.5
                            },
                            {
                                "name": "Over",
                                "description": "Jayson Tatum",
                                "price": 1.83,
                                "point": 9.5
                            },
                            {
                                "name": "Under",
                                "description": "Jayson Tatum",
                                "price": 1.91,
                                "point": 9.5
                            },
                            {
                                "name": "Over",
                                "description": "Murray Dejounte",
                                "price": 2.1,
                                "point": 4.5
                            },
                            {
                                "name": "Under",
                                "description": "Murray Dejounte",
                                "price": 1.69,
                                "point": 4.5
                            },
                            {
                                "name": "Over",
                                "description": "Trae Young",
                                "price": 2.35,
                                "point": 3.5
                            },
                            {
                                "name": "Under",
                                "description": "Trae Young",
                                "price": 1.56,
                                "point": 3.5
                            }
                        ]
                    }
                ]
            }
        ]
    }
}