{
    "timestamp": "2024-02-05T09:55:38Z",
    "previous_timestamp": "2024-02-05T09:50:37Z",
    "next_timestamp": "2024-02-05T10:00:38Z",
    "data": {
        "id": "c57c67cfb539cf4c05362a523bddb5c6",
        "sport_key": "basketball_nba",
        "sport_title": "NBA",
        "commence_time": "2024-02-06T00:10:00Z",
        "home_team": "Charlotte Hornets",
        "away_team": "Los Angeles Lakers",
        "bookmakers": [
            {
                "key": "draftkings",
                "title": "DraftKings",
                "last_update": "2024-02-05T09:54:29Z",
                "markets": [
                    {
                        "key": "player_assists",
                        "last_update": "2024-02-05T09:54:11Z",
                        "outcomes": [
                            {
                                "name": "Over",
                                "description": "Anthony Davis",
                                "price": 1.56,
                                "point": 3.5
                            },
                            {
                                "name": "Under",
                                "description": "Anthony Davis",
                                "price": 2.4,
                                "point": 3.5
                            },
                            {
                                "name": "Over",
                                "description": "Austin Reaves",
                                "price": 1.87,
                                "point": 5.5
                            },
                            {
                                "name": "Under",
                                "description": "Austin Reaves",
                                "price": 1.87,
                                "point": 5.5
                            },
                            {
                                "name": "Over",
                                "description": "D'Angelo Russell",
                                "price": 1.95,
                                "point": 6.5
                            },
                            {
                                "name": "Under",
                                "description": "D'Angelo Russell",
                                "price": 1.8,
                                "point": 6.5
                            },
                            {
                                "name": "Over",
                                "description": "LeBron James",
                                "price": 2.0,
                                "point": 8.5
                            },
                            {
                                "name": "Under",
                                "description": "LeBron James",
                                "price": 1.77,
                                "point": 8.5
                            }
                        ]
                    },
                    {
                        "key": "player_points",
                        "last_update": "2024-02-05T09:54:11Z",
                        "outcomes": [
                            {
                                "name": "Over",
                                "description": "Anthony Davis",
                                "price": 1.87,
                                "point": 26.5
                            },
                            {
                                "name": "Under",
                                "description": "Anthony Davis",
                                "price": 1.87,
                                "point": 26.5
                            },
                            {
                                "name": "Over",
                                "description": "Austin Reaves",
                                "price": 1.83,
                                "point": 16.5
                            },
                            {
                                "name": "Under",
                                "description": "Austin Reaves",
                                "price": 1.91,
                                "point": 16.5
                            },
                            {
                                "name": "Over",
                                "description": "D'Angelo Russell",
                                "price": 1.83,
                                "point": 17.5
                            },
                            {
                                "name": "Under",
                                "description": "D'Angelo Russell",
                                "price": 1.91,
                                "point": 17.5
                            },
                            {
                                "name": "Over",
                                "description": "LeBron James",
                                "price": 1.87,
                                "point": 24.5
                            },
                            {
                                "name": "Under",
                                "description": "LeBron James",
                                "price": 1.87,
                                "point": 24.5
                            }
                        ]
                    },
                    {
                        "key": "player_rebounds",
                        "last_update": "2024-02-05T09:54:11Z",
                        "outcomes": [
                            {
                                "name": "Over",
                                "description": "Anthony Davis",
                                "price": 1.77,
                                "point": 12.5
                            },
                            {
                                "name": "Under",
                                "description": "Anthony Davis",
                                "price": 2.0,
                                "point": 12.5
                            },
                            {
                                "name": "Over",
                                "description": "Austin Reaves",
                                "price": 1.69,
                                "point": 3.5
                            },
                            {
                                "name": "Under",
                                "description": "Austin Reaves",
                                "price": 2.14,
                                "point": 3.5
                            },
                            {
                                "name": "Over",
                                "description": "D'Angelo Russell",
                                "price": 1.6,
                                "point": 2.5
                            },
                            {
                                "name": "Under",
                                "description": "D'Angelo Russell",
                                "price": 2.3,
                                "point": 2.5
                            },
                            {
                                "name": "Over",
                                "description": "LeBron James",
                                "price": 1.8,
                                "point": 7.5
                            },
                            {
                                "name": "Under",
                                "description": "LeBron James",
                                "price": 1.95,
                                "point": 7.5
                            }
                        ]
                    }
                ]
            },
            {
                "key": "fanduel",
                "title": "FanDuel",
                "last_update": "2024-02-05T09:53:52Z",
                "markets": [
                    {
                        "key": "player_assists",
                        "last_update": "2024-02-05T09:55:13Z",
                        "outcomes": [
                            {
                                "name": "Over",
                                "description": "D'Angelo Russell",
                                "price": 1.88,
                                "point": 6.5
                            },
                            {
                                "name": "Under",
                                "description": "D'Angelo Russell",
                                "price": 1.88,
                                "point": 6.5
                            },
                            {
                                "name": "Over",
                                "description": "LeBron James",
                                "price": 2.14,
                                "point": 8.5
                            },
                            {
                                "name": "Under",
                                "description": "LeBron James",
                                "price": 1.68,
                                "point": 8.5
                            },
                            {
                                "name": "Over",
                                "description": "Miles Bridges",
                                "price": 1.77,
                                "point": 3.5
                            },
                            {
                                "name": "Under",
                                "description": "Miles Bridges",
                                "price": 2.02,
                                "point": 3.5
                            },
                            {
                                "name": "Over",
                                "description": "Anthony Davis",
                                "price": 1.65,
                                "point": 3.5
                            },
                            {
                                "name": "Under",
                                "description": "Anthony Davis",
                                "price": 2.2,
                                "point": 3.5
                            },
                            {
                                "name": "Over",
                                "description": "Austin Reaves",
                                "price": 1.96,
                                "point": 5.5
                            },
                            {
                                "name": "Under",
                                "description": "Austin Reaves",
                                "price": 1.83,
                                "point": 5.5
                            }
                        ]
                    },
                    {
                        "key": "player_points",
                        "last_update": "2024-02-05T09:55:13Z",
                        "outcomes": [
                            {
                                "name": "Over",
                                "description": "Anthony Davis",
                                "price": 1.88,
                                "point": 26.5
                            },
                            {
                                "name": "Under",
                                "description": "Anthony Davis",
                                "price": 1.88,
                                "point": 26.5
                            },
                            {
                                "name": "Over",
                                "description": "Austin Reaves",
                                "price": 1.85,
                                "point": 15.5
                            },
                            {
                                "name": "Under",
                                "description": "Austin Reaves",
                                "price": 1.93,
                                "point": 15.5
                            },
                            {
                                "name": "Over",
                                "description": "Brandon Miller",
                                "price": 1.82,
                                "point": 22.5
                            },
                            {
                                "name": "Under",
                                "description": "Brandon Miller",
                                "price": 1.96,
                                "point": 22.5
                            },
                            {
                                "name": "Over",
                                "description": "LeBron James",
                                "price": 1.9,
                                "point": 24.5
                            },
                            {
                                "name": "Under",
                                "description": "LeBron James",
                                "price": 1.87,
                                "point": 24.5
                            },
                            {
                                "name": "Over",
                                "description": "Miles Bridges",
                                "price": 1.9,
                                "point": 24.5
                            },
                            {
                                "name": "Under",
                                "description": "Miles Bridges",
                                "price": 1.87,
                                "point": 24.5
                            },
                            {
                                "name": "Over",
                                "description": "D'Angelo Russell",
                                "price": 1.94,
                                "point": 17.5
                            },
                            {
                                "name": "Under",
                                "description": "D'Angelo Russell",
                                "price": 1.83,
                                "point": 17.5
                            }
                        ]
                    },
                    {
                        "key": "player_rebounds",
                        "last_update": "2024-02-05T09:55:13Z",
                        "outcomes": [
                            {
                                "name": "Over",
                                "description": "Miles Bridges",
                                "price": 1.87,
                                "point": 7.5
                            },
                            {
                                "name": "Under",
                                "description": "Miles Bridges",
                                "price": 1.9,
                                "point": 7.5
                            },
                            {
                                "name": "Over",
                                "description": "Anthony Davis",
                                "price": 1.94,
                                "point": 12.5
                            },
                            {
                                "name": "Under",
                                "description": "Anthony Davis",
                                "price": 1.83,
                                "point": 12.5
                            },
                            {
                                "name": "Over",
                                "description": "D'Angelo Russell",
                                "price": 1.62,
                                "point": 2.5
                            },
                            {
                                "name": "Under",
                                "description": "D'Angelo Russell",
                                "price": 2.24,
                                "point": 2.5
                            },
                            {
                                "name": "Over",
                                "description": "Brandon Miller",
                                "price": 1.93,
                                "point": 4.5
                            },
                            {
                                "name": "Under",
                                "description": "Brandon Miller",
                                "price": 1.85,
                                "point": 4.5
                            },
                            {
                                "name": "Over",
                                "description": "Austin Reaves",
                                "price": 1.68,
                                "point": 3.5
                            },
                            {
                                "name": "Under",
                                "description": "Austin Reaves",
                                "price": 2.14,
                                "point": 3.5
                            },
                            {
                                "name": "Over",
                                "description": "LeBron James",
                                "price": 1.87,
                                "point": 7.5
                            },
                            {
                                "name": "Under",
                                "description": "LeBron James",
                                "price": 1.9,
                                "point": 7.5
                            }
                        ]
                    }
                ]
            },
            {
                "key": "pointsbetus",
                "title": "PointsBet (US)",
                "last_update": "2024-02-05T09:53:58Z",
                "markets": [
                    {
                        "key": "player_assists",
                        "last_update": "2024-02-05T09:55:47Z",
                        "outcomes": [
                            {
                                "name": "Over",
                                "description": "Anthony Davis",
                                "price": 2.25,
                                "point": 4.5
                            },
                            {
                                "name": "Under",
                                "description": "Anthony Davis",
                                "price": 1.61,
                                "point": 4.5
                            },
                            {
                                "name": "Over",
                                "description": "Austin Reaves",
                                "price": 1.87,
                                "point": 5.5
                            },
                            {
                                "name": "Under",
                                "description": "Austin Reaves",
                                "price": 1.87,
                                "point": 5.5
                            },
                            {
                                "name": "Over",
                                "description": "D'Angelo Russell",
                                "price": 1.95,
                                "point": 6.5
                            },
                            {
                                "name": "Under",
                                "description": "D'Angelo Russell",
                                "price": 1.8,
                                "point": 6.5
                            },
                            {
                                "name": "Over",
                                "description": "LeBron James",
                                "price": 2.0,
                                "point": 8.5
                            },
                            {
                                "name": "Under",
                                "description": "LeBron James",
                                "price": 1.77,
                                "point": 8.5
                            }
                        ]
                    },
                    {
                        "key": "player_points",
                        "last_update": "2024-02-05T09:55:47Z",
                        "outcomes": [
                            {
                                "name": "Over",
                                "description": "Anthony Davis",
                                "price": 1.87,
                                "point": 26.5
                            },
                            {
                                "name": "Under",
                                "description": "Anthony Davis",
                                "price": 1.87,
                                "point": 26.5
                            },
                            {
                                "name": "Over",
                                "description": "Austin Reaves",
                                "price": 1.87,
                                "point": 16.5
                            },
                            {
                                "name": "Under",
                                "description": "Austin Reaves",
                                "price": 1.87,
                                "point": 16.5
                            },
                            {
                                "name": "Over",
                                "description": "D'Angelo Russell",
                                "price": 1.87,
                                "point": 17.5
                            },
                            {
                                "name": "Under",
                                "description": "D'Angelo Russell",
                                "price": 1.87,
                                "point": 17.5
                            },
                            {
                                "name": "Over",
                                "description": "LeBron James",
                                "price": 1.87,
                                "point": 24.5
                            },
                            {
                                "name": "Under",
                                "description": "LeBron James",
                                "price": 1.87,
                                "point": 24.5
                            }
                        ]
                    },
                    {
                        "key": "player_rebounds",
                        "last_update": "2024-02-05T09:55:47Z",
                        "outcomes": [
                            {
                                "name": "Over",
                                "description": "Anthony Davis",
                                "price": 1.71,
                                "point": 12.5
                            },
                            {
                                "name": "Under",
                                "description": "Anthony Davis",
                                "price": 2.05,
                                "point": 12.5
                            },
                            {
                                "name": "Over",
                                "description": "Austin Reaves",
                                "price": 1.69,
                                "point": 3.5
                            },
                            {
                                "name": "Under",
                                "description": "Austin Reaves",
                                "price": 2.1,
                                "point": 3.5
                            },
                            {
                                "name": "Over",
                                "description": "D'Angelo Russell",
                                "price": 1.59,
                                "point": 2.5
                            },
                            {
                                "name": "Under",
                                "description": "D'Angelo Russell",
                                "price": 2.3,
                                "point": 2.5
                            },
                            {
                                "name": "Over",
                                "description": "LeBron James",
                                "price": 1.8,
                                "point": 7.5
                            },
                            {
                                "name": "Under",
                                "description": "LeBron James",
                                "price": 1.95,
                                "point": 7.5
                            }
                        ]
                    }
                ]
            },
            {
                "key": "bovada",
                "title": "Bovada",
                "last_update": "2024-02-05T09:53:48Z",
                "markets": [
                    {
                        "key": "player_assists",
                        "last_update": "2024-02-05T09:53:58Z",
                        "outcomes": [
                            {
                                "name": "Over",
                                "description": "Anthony Davis Jr.",
                                "price": 1.62,
                                "point": 3.5
                            },
                            {
                                "name": "Under",
                                "description": "Anthony Davis Jr.",
                                "price": 2.2,
                                "point": 3.5
                            },
                            {
                                "name": "Over",
                                "description": "Austin Reaves",
                                "price": 1.87,
                                "point": 5.5
                            },
                            {
                                "name": "Under",
                                "description": "Austin Reaves",
                                "price": 1.87,
                                "point": 5.5
                            },
                            {
                                "name": "Over",
                                "description": "D'Angelo Russell",
                                "price": 1.95,
                                "point": 6.5
                            },
                            {
                                "name": "Under",
                                "description": "D'Angelo Russell",
                                "price": 1.8,
                                "point": 6.5
                            },
                            {
                                "name": "Over",
                                "description": "LeBron James",
                                "price": 2.05,
                                "point": 8.5
                            },
                            {
                                "name": "Under",
                                "description": "LeBron James",
                                "price": 1.74,
                                "point": 8.5
                            }
                        ]
                    },
                    {
                        "key": "player_points",
                        "last_update": "2024-02-05T09:53:58Z",
                        "outcomes": [
                            {
                                "name": "Over",
                                "description": "Anthony Davis Jr.",
                                "price": 1.91,
                                "point": 26.5
                            },
                            {
                                "name": "Under",
                                "description": "Anthony Davis Jr.",
                                "price": 1.83,
                                "point": 26.5
                            },
                            {
                                "name": "Over",
                                "description": "Austin Reaves",
                                "price": 1.83,
                                "point": 15.5
                            },
                            {
                                "name": "Under",
                                "description": "Austin Reaves",
                                "price": 1.91,
                                "point": 15.5
                            },
                            {
                                "name": "Over",
                                "description": "Brandon Miller",
                                "price": 1.74,
                                "point": 22.5
                            },
                            {
                                "name": "Under",
                                "description": "Brandon Miller",
                                "price": 2.05,
                                "point": 22.5
                            },
                            {
                                "name": "Over",
                                "description": "D'Angelo Russell",
                                "price": 1.83,
                                "point": 17.5
                            },
                            {
                                "name": "Under",
                                "description": "D'Angelo Russell",
                                "price": 1.91,
                                "point": 17.5
                            },
                            {
                                "name": "Over",
                                "description": "LeBron James",
                                "price": 1.91,
                                "point": 24.5
                            },
                            {
                                "name": "Under",
                                "description": "LeBron James",
                                "price": 1.83,
                                "point": 24.5
                            },
                            {
                                "name": "Over",
                                "description": "Miles Bridges",
                                "price": 2.05,
                                "point": 24.5
                            },
                            {
                                "name": "Under",
                                "description": "Miles Bridges",
                                "price": 1.74,
                                "point": 24.5
                            }
                        ]
                    },
                    {
                        "key": "player_rebounds",
                        "last_update": "2024-02-05T09:53:58Z",
                        "outcomes": [
                            {
                                "name": "Over",
                                "description": "Anthony Davis Jr.",
                                "price": 1.77,
                                "point": 12.5
                            },
                            {
                                "name": "Under",
                                "description": "Anthony Davis Jr.",
                                "price": 2.0,
                                "point": 12.5
                            },
                            {
                                "name": "Over",
                                "description": "Austin Reaves",
                                "price": 1.69,
                                "point": 3.5
                            },
                            {
                                "name": "Under",
                                "description": "Austin Reaves",
                                "price": 2.1,
                                "point": 3.5
                            },
                            {
                                "name": "Over",
                                "description": "D'Angelo Russell",
                                "price": 1.59,
                                "point": 2.5
                            },
                            {
                                "name": "Under",
                                "description": "D'Angelo Russell",
                                "price": 2.3,
                                "point": 2.5
                            },
                            {
                                "name": "Over",
                                "description": "LeBron James",
                                "price": 1.8,
                                "point": 7.5
                            },
                            {
                                "name": "Under",
                                "description": "LeBron James",
                                "price": 1.95,
                                "point": 7.5
                            }
                        ]
                    }
                ]
            },
            {
                "key": "williamhill_us",
                "title": "Caesars",
                "last_update": "2024-02-05T09:52:23Z",
                "markets": [
                    {
                        "key": "player_assists",
                        "last_update": "2024-02-05T09:54:15Z",
                        "outcomes": [
                            {
                                "name": "Over",
                                "description": "Austin Reaves",
                                "price": 1.92,
                                "point": 5.5
                            },
                            {
                                "name": "Under",
                                "description": "Austin Reaves",
                                "price": 1.8,
                                "point": 5.5
                            },
                            {
                                "name": "Over",
                                "description": "LeBron James",
                                "price": 1.96,
                                "point": 8.5
                            },
                            {
                                "name": "Under",
                                "description": "LeBron James",
                                "price": 1.76,
                                "point": 8.5
                            },
                            {
                                "name": "Over",
                                "description": "D'Angelo Russell",
                                "price": 1.97,
                                "point": 6.5
                            },
                            {
                                "name": "Under",
                                "description": "D'Angelo Russell",
                                "price": 1.75,
                                "point": 6.5
                            },
                            {
                                "name": "Over",
                                "description": "Anthony Davis",
                                "price": 1.6,
                                "point": 3.5
                            },
                            {
                                "name": "Under",
                                "description": "Anthony Davis",
                                "price": 2.2,
                                "point": 3.5
                            }
                        ]
                    },
                    {
                        "key": "player_points",
                        "last_update": "2024-02-05T09:54:15Z",
                        "outcomes": [
                            {
                                "name": "Over",
                                "description": "Anthony Davis",
                                "price": 1.88,
                                "point": 26.5
                            },
                            {
                                "name": "Under",
                                "description": "Anthony Davis",
                                "price": 1.83,
                                "point": 26.5
                            },
                            {
                                "name": "Over",
                                "description": "D'Angelo Russell",
                                "price": 1.8,
                                "point": 17.5
                            },
                            {
                                "name": "Under",
                                "description": "D'Angelo Russell",
                                "price": 1.92,
                                "point": 17.5
                            },
                            {
                                "name": "Over",
                                "description": "Austin Reaves",
                                "price": 1.96,
                                "point": 16.5
                            },
                            {
                                "name": "Under",
                                "description": "Austin Reaves",
                                "price": 1.76,
                                "point": 16.5
                            },
                            {
                                "name": "Over",
                                "description": "LeBron James",
                                "price": 1.83,
                                "point": 24.5
                            },
                            {
                                "name": "Under",
                                "description": "LeBron James",
                                "price": 1.88,
                                "point": 24.5
                            }
                        ]
                    },
                    {
                        "key": "player_rebounds",
                        "last_update": "2024-02-05T09:54:15Z",
                        "outcomes": [
                            {
                                "name": "Over",
                                "description": "Austin Reaves",
                                "price": 1.69,
                                "point": 3.5
                            },
                            {
                                "name": "Under",
                                "description": "Austin Reaves",
                                "price": 2.06,
                                "point": 3.5
                            },
                            {
                                "name": "Over",
                                "description": "Anthony Davis",
                                "price": 1.88,
                                "point": 12.5
                            },
                            {
                                "name": "Under",
                                "description": "Anthony Davis",
                                "price": 1.83,
                                "point": 12.5
                            },
                            {
                                "name": "Over",
                                "description": "LeBron James",
                                "price": 1.83,
                                "point": 7.5
                            },
                            {
                                "name": "Under",
                                "description": "LeBron James",
                                "price": 1.88,
                                "point": 7.5
                            },
                            {
                                "name": "Over",
                                "description": "D'Angelo Russell",
                                "price": 1.6,
                                "point": 2.5
                            },
                            {
                                "name": "Under",
                                "description": "D'Angelo Russell",
                                "price": 2.2,
                                "point": 2.5
                            }
                        ]
                    }
                ]
            },
            {
                "key": "betmgm",
                "title": "BetMGM",
                "last_update": "2024-02-05T09:55:35Z",
                "markets": [
                    {
                        "key": "player_assists",
                        "last_update": "2024-02-05T09:53:00Z",
                        "outcomes": [
                            {
                                "name": "Over",
                                "description": "Anthony Davis",
                                "price": 1.61,
                                "point": 3.5
                            },
                            {
                                "name": "Under",
                                "description": "Anthony Davis",
                                "price": 2.25,
                                "point": 3.5
                            },
                            {
                                "name": "Over",
                                "description": "Austin Reaves",
                                "price": 1.87,
                                "point": 5.5
                            },
                            {
                                "name": "Under",
                                "description": "Austin Reaves",
                                "price": 1.87,
                                "point": 5.5
                            },
                            {
                                "name": "Over",
                                "description": "D'Angelo Russell",
                                "price": 1.95,
                                "point": 6.5
                            },
                            {
                                "name": "Under",
                                "description": "D'Angelo Russell",
                                "price": 1.8,
                                "point": 6.5
                            },
                            {
                                "name": "Over",
                                "description": "LeBron James",
                                "price": 2.0,
                                "point": 8.5
                            },
                            {
                                "name": "Under",
                                "description": "LeBron James",
                                "price": 1.74,
                                "point": 8.5
                            }
                        ]
                    },
                    {
                        "key": "player_points",
                        "last_update": "2024-02-05T09:53:00Z",
                        "outcomes": [
                            {
                                "name": "Over",
                                "description": "Anthony Davis",
                                "price": 1.87,
                                "point": 26.5
                            },
                            {
                                "name": "Under",
                                "description": "Anthony Davis",
                                "price": 1.83,
                                "point": 26.5
                            },
                            {
                                "name": "Over",
                                "description": "D'Angelo Russell",
                                "price": 1.83,
                                "point": 17.5
                            },
                            {
                                "name": "Under",
                                "description": "D'Angelo Russell",
                                "price": 1.91,
                                "point": 17.5
                            },
                            {
                                "name": "Over",
                                "description": "LeBron James",
                                "price": 1.83,
                                "point": 24.5
                            },
                            {
                                "name": "Under",
                                "description": "LeBron James",
                                "price": 1.87,
                                "point": 24.5
                            },
                            {
                                "name": "Over",
                                "description": "Austin Reaves",
                                "price": 2.0,
                                "point": 16.5
                            },
                            {
                                "name": "Under",
                                "description": "Austin Reaves",
                                "price": 1.77,
                                "point": 16.5
                            }
                        ]
                    },
                    {
                        "key": "player_rebounds",
                        "last_update": "2024-02-05T09:53:00Z",
                        "outcomes": [
                            {
                                "name": "Over",
                                "description": "Anthony Davis",
                                "price": 1.91,
                                "point": 12.5
                            },
                            {
                                "name": "Under",
                                "description": "Anthony Davis",
                                "price": 1.83,
                                "point": 12.5
                            },
                            {
                                "name": "Over",
                                "description": "Austin Reaves",
                                "price": 1.67,
                                "point": 3.5
                            },
                            {
                                "name": "Under",
                                "description": "Austin Reaves",
                                "price": 2.1,
                                "point": 3.5
                            },
                            {
                                "name": "Over",
                                "description": "D'Angelo Russell",
                                "price": 1.57,
                                "point": 2.5
                            },
                            {
                                "name": "Under",
                                "description": "D'Angelo Russell",
                                "price": 2.3,
                                "point": 2.5
                            },
                            {
                                "name": "Over",
                                "description": "LeBron James",
                                "price": 1.8,
                                "point": 7.5
                            },
                            {
                                "name": "Under",
                                "description": "LeBron James",
                                "price": 1.95,
                                "point": 7.5
                            }
                        ]
                    }
                ]
            },
            {
                "key": "betonlineag",
                "title": "BetOnline.ag",
                "last_update": "2024-02-05T09:55:26Z",
                "markets": [
                    {
                        "key": "player_assists",
                        "last_update": "2024-02-05T09:55:41Z",
                        "outcomes": [
                            {
                                "name": "Over",
                                "description": "D'Angelo Russell",
                                "price": 1.92,
                                "point": 6.5
                            },
                            {
                                "name": "Under",
                                "description": "D'Angelo Russell",
                                "price": 1.84,
                                "point": 6.5
                            },
                            {
                                "name": "Under",
                                "description": "Miles Bridges",
                                "price": 2.04,
                                "point": 3.5
                            },
                            {
                                "name": "Over",
                                "description": "Miles Bridges",
                                "price": 1.74,
                                "point": 3.5
                            },
                            {
                                "name": "Over",
                                "description": "Anthony Davis Jr.",
                                "price": 1.6,
                                "point": 3.5
                            },
                            {
                                "name": "Under",
                                "description": "Anthony Davis Jr.",
                                "price": 2.27,
                                "point": 3.5
                            },
                            {
                                "name": "Over",
                                "description": "LeBron James",
                                "price": 2.1,
                                "point": 8.5
                            },
                            {
                                "name": "Under",
                                "description": "LeBron James",
                                "price": 1.7,
                                "point": 8.5
                            },
                            {
                                "name": "Over",
                                "description": "Austin Reaves",
                                "price": 1.9,
                                "point": 5.5
                            },
                            {
                                "name": "Under",
                                "description": "Austin Reaves",
                                "price": 1.86,
                                "point": 5.5
                            }
                        ]
                    },
                    {
                        "key": "player_points",
                        "last_update": "2024-02-05T09:55:41Z",
                        "outcomes": [
                            {
                                "name": "Over",
                                "description": "LeBron James",
                                "price": 1.91,
                                "point": 24.5
                            },
                            {
                                "name": "Under",
                                "description": "LeBron James",
                                "price": 1.85,
                                "point": 24.5
                            },
                            {
                                "name": "Over",
                                "description": "Miles Bridges",
                                "price": 1.95,
                                "point": 24.5
                            },
                            {
                                "name": "Under",
                                "description": "Miles Bridges",
                                "price": 1.81,
                                "point": 24.5
                            },
                            {
                                "name": "Over",
                                "description": "Anthony Davis Jr.",
                                "price": 1.9,
                                "point": 26.5
                            },
                            {
                                "name": "Under",
                                "description": "Anthony Davis Jr.",
                                "price": 1.86,
                                "point": 26.5
                            },
                            {
                                "name": "Under",
                                "description": "D'Angelo Russell",
                                "price": 1.88,
                                "point": 17.5
                            },
                            {
                                "name": "Over",
                                "description": "D'Angelo Russell",
                                "price": 1.88,
                                "point": 17.5
                            },
                            {
                                "name": "Over",
                                "description": "Brandon Miller",
                                "price": 1.77,
                                "point": 22.5
                            },
                            {
                                "name": "Under",
                                "description": "Brandon Miller",
                                "price": 2.0,
                                "point": 22.5
                            },
                            {
                                "name": "Over",
                                "description": "Austin Reaves",
                                "price": 1.89,
                                "point": 16.5
                            },
                            {
                                "name": "Under",
                                "description": "Austin Reaves",
                                "price": 1.87,
                                "point": 16.5
                            }
                        ]
                    },
                    {
                        "key": "player_rebounds",
                        "last_update": "2024-02-05T09:55:41Z",
                        "outcomes": [
                            {
                                "name": "Over",
                                "description": "D'Angelo Russell",
                                "price": 1.6,
                                "point": 2.5
                            },
                            {
                                "name": "Under",
                                "description": "D'Angelo Russell",
                                "price": 2.28,
                                "point": 2.5
                            },
                            {
                                "name": "Over",
                                "description": "Miles Bridges",
                                "price": 1.86,
                                "point": 7.5
                            },
                            {
                                "name": "Under",
                                "description": "Miles Bridges",
                                "price": 1.9,
                                "point": 7.5
                            },
                            {
                                "name": "Under",
                                "description": "LeBron James",
                                "price": 1.92,
                                "point": 7.5
                            },
                            {
                                "name": "Over",
                                "description": "LeBron James",
                                "price": 1.84,
                                "point": 7.5
                            },
                            {
                                "name": "Under",
                                "description": "Anthony Davis Jr.",
                                "price": 1.91,
                                "point": 12.5
                            },
                            {
                                "name": "Over",
                                "description": "Anthony Davis Jr.",
                                "price": 1.85,
                                "point": 12.5
                            },
                            {
                                "name": "Under",
                                "description": "Austin Reaves",
                                "price": 2.11,
                                "point": 3.5
                            },
                            {
                                "name": "Over",
                                "description": "Austin Reaves",
                                "price": 1.69,
                                "point": 3.5
                            },
                            {
                                "name": "Over",
                                "description": "Brandon Miller",
                                "price": 1.91,
                                "point": 4.5
                            },
                            {
                                "name": "Under",
                                "description": "Brandon Miller",
                                "price": 1.85,
                                "point": 4.5
                            }
                        ]
                    }
                ]
            }
        ]
    }
}